<?xml version="1.0" encoding="UTF-8"?>
<!--
Created with Free texture packer v0.6.7 http://free-tex-packer.com
Format:
n  => name
x  => x pos
y  => y pos
w  => width
h  => height
pX => x pos of the pivot point
pY => y pos of the pivot point
oX => x-corner offset
oY => y-corner offset
oW => original width
oH => original height
r => 'y' if sprite is rotated-->
<TextureAtlas imagePath="enemy.png" width="1024" height="128" scale="1" format="RGBA8888">
  <sprite n="image_003_0000.png" x="0" y="0" w="64" h="64" pX="0.5" pY="0.5"/>
  <sprite n="image_003_0001.png" x="0" y="64" w="64" h="64" pX="0.5" pY="0.5"/>
  <sprite n="image_003_0002.png" x="64" y="0" w="64" h="64" pX="0.5" pY="0.5"/>
  <sprite n="image_003_0003.png" x="64" y="64" w="64" h="64" pX="0.5" pY="0.5"/>
  <sprite n="image_003_0004.png" x="128" y="0" w="64" h="64" pX="0.5" pY="0.5"/>
  <sprite n="image_003_0005.png" x="128" y="64" w="64" h="64" pX="0.5" pY="0.5"/>
  <sprite n="image_003_0006.png" x="192" y="0" w="64" h="64" pX="0.5" pY="0.5"/>
  <sprite n="image_003_0007.png" x="192" y="64" w="64" h="64" pX="0.5" pY="0.5"/>
  <sprite n="image_003_0008.png" x="256" y="0" w="64" h="64" pX="0.5" pY="0.5"/>
  <sprite n="image_003_0009.png" x="256" y="64" w="64" h="64" pX="0.5" pY="0.5"/>
  <sprite n="image_003_0010.png" x="320" y="0" w="64" h="64" pX="0.5" pY="0.5"/>
  <sprite n="image_003_0011.png" x="320" y="64" w="64" h="64" pX="0.5" pY="0.5"/>
  <sprite n="image_003_0012.png" x="384" y="0" w="64" h="64" pX="0.5" pY="0.5"/>
  <sprite n="image_003_0013.png" x="384" y="64" w="64" h="64" pX="0.5" pY="0.5"/>
  <sprite n="image_003_0014.png" x="448" y="0" w="64" h="64" pX="0.5" pY="0.5"/>
  <sprite n="image_003_0015.png" x="448" y="64" w="64" h="64" pX="0.5" pY="0.5"/>
  <sprite n="image_003_0016.png" x="512" y="0" w="64" h="64" pX="0.5" pY="0.5"/>
  <sprite n="image_003_0017.png" x="512" y="64" w="64" h="64" pX="0.5" pY="0.5"/>
  <sprite n="image_003_0018.png" x="576" y="0" w="64" h="64" pX="0.5" pY="0.5"/>
  <sprite n="image_003_0019.png" x="576" y="64" w="64" h="64" pX="0.5" pY="0.5"/>
  <sprite n="image_003_0020.png" x="640" y="0" w="64" h="64" pX="0.5" pY="0.5"/>
  <sprite n="image_003_0021.png" x="640" y="64" w="64" h="64" pX="0.5" pY="0.5"/>
  <sprite n="image_003_0022.png" x="704" y="0" w="64" h="64" pX="0.5" pY="0.5"/>
  <sprite n="image_003_0023.png" x="704" y="64" w="64" h="64" pX="0.5" pY="0.5"/>
  <sprite n="image_003_0024.png" x="768" y="0" w="64" h="64" pX="0.5" pY="0.5"/>
  <sprite n="image_003_0025.png" x="768" y="64" w="64" h="64" pX="0.5" pY="0.5"/>
  <sprite n="image_003_0026.png" x="832" y="0" w="64" h="64" pX="0.5" pY="0.5"/>
  <sprite n="image_003_0027.png" x="832" y="64" w="64" h="64" pX="0.5" pY="0.5"/>
  <sprite n="image_003_0028.png" x="896" y="0" w="64" h="64" pX="0.5" pY="0.5"/>
  <sprite n="image_003_0029.png" x="896" y="64" w="64" h="64" pX="0.5" pY="0.5"/>
  <sprite n="image_003_0030.png" x="960" y="0" w="64" h="64" pX="0.5" pY="0.5"/>
</TextureAtlas>